setup.py
src/txCarbonClient/__init__.py
src/txCarbonClient/carbon_client_factory.py
src/txCarbonClient/carbon_client_protocol.py
src/txCarbonClient/carbon_client_service.py
src/txCarbonClient/repeating_metric_handle.py
src/txCarbonClient.egg-info/PKG-INFO
src/txCarbonClient.egg-info/SOURCES.txt
src/txCarbonClient.egg-info/dependency_links.txt
src/txCarbonClient.egg-info/requires.txt
src/txCarbonClient.egg-info/top_level.txt
test/test_carbon_client.py