Metadata-Version: 1.1
Name: txCarbonClient
Version: 0.1
Summary: A simple Twisted client for reporting metrics to Carbon.
Home-page: https://github.com/fdChasm/txCarbonClient
Author: Chasm
Author-email: fd.chasm@gmail.com
License: MIT
Platform: UNKNOWN
Classifier: Development Status :: 3 - Alpha
Classifier: Topic :: Software Development :: Libraries :: Python Modules
Classifier: License :: OSI Approved :: MIT License
Classifier: Natural Language :: English
